qualia/__init__.py
qualia/client.py
qualia/exceptions.py
qualia/models.py
qualia/py.typed
qualia/resources/__init__.py
qualia/resources/base.py
qualia/resources/credits.py
qualia/resources/datasets.py
qualia/resources/finetune.py
qualia/resources/instances.py
qualia/resources/models.py
qualia/resources/projects.py
qualia_sdk-0.1.1.dist-info/METADATA
qualia_sdk-0.1.1.dist-info/WHEEL
qualia_sdk-0.1.1.dist-info/RECORD
