Metadata-Version: 2.4
Name: qualia-sdk
Version: 0.1.1
Summary: Python SDK for Qualia Studios VLA fine-tuning platform
Project-URL: Homepage, https://qualiastudios.dev
Project-URL: Documentation, https://docs.qualiastudios.dev
Author: Qualia Studios
License-Expression: MIT
Keywords: fine-tuning,machine-learning,qualia,robotics,vla
Classifier: Development Status :: 4 - Beta
Classifier: Intended Audience :: Developers
Classifier: License :: OSI Approved :: MIT License
Classifier: Programming Language :: Python :: 3
Classifier: Programming Language :: Python :: 3.10
Classifier: Programming Language :: Python :: 3.11
Classifier: Programming Language :: Python :: 3.12
Classifier: Typing :: Typed
Requires-Python: >=3.10
Requires-Dist: httpx>=0.25.0
Requires-Dist: opentelemetry-api>=1.20.0
Requires-Dist: opentelemetry-instrumentation-httpx>=0.41b0
Requires-Dist: pydantic>=2.0.0
